monocle/__init__.py
monocle/callback.py
monocle/core.py
monocle/experimental.py
monocle/monocle_mock.py
monocle/script_util.py
monocle/util.py
monocle/stack/eventloop.py
monocle/stack/network/__init__.py
monocle/stack/network/http.py
tricle-1.8.dist-info/METADATA
tricle-1.8.dist-info/WHEEL
tricle-1.8.dist-info/top_level.txt
tricle-1.8.dist-info/RECORD
